seq_gen.v
module seq_gen(input wire load, clk, output wire [3:0] out);
tff g1(clk,out[0],1,out[0]);
tff g2(clk,out[1],1,out[1]);
tff g3(clk,out[2],1,out[2]);
tff g4(clk,out[3],1,out[3]);
endmodule

module sequencegenerator(input clk, reset,output s3);
 
     reg s1, s2, s3;
     wire s0;
 
     assign s0 = s1 ^ s3;
     //using bitwise exclusive exclusive or to finding the value of s0

     // STATE MACHINE
     always @ (posedge clk or reset)

     begin 
          // INITIAL STATE SHOULDN'T BE 000 => 100
          //here 000 initial input leads to sequence of 000...
          //so depending on the input here we can generate the 
          //required sequence that we wanted
          //here input is 100


          if(reset) begin//@beginning the input should be 100
               s1 <= 1;
               s2 <= 0;
               s3 <= 0;
          end 
          else begin   //else moving the sequence 
               s1 <= s0;
               s2 <= s1;
               s3 <= s2;
          end
     end
     //returing the output s3 every time

endmodule

tb_seq_gen.v
`timescale 1ns / 1ps


module Test_sequencegenerator;
       // Inputs
       reg clk;
       reg reset;
       // Outputs
       wire s3;

 // Instantiate the  Sequence Generator Test (SGT)

 sequencegenerator SGT (.clk(clk), .reset(reset), .s3(s3));


 initial begin


  $dumpfile("Sequence.vcd");
	$dumpvars;

  // Initialize Inputs
  clk = 0;
  reset = 0;

  // Wait 100 ns for global reset to finish
  //#100;

  // Add stimulus here
  #10 reset = 1;
  #10 reset = 0;
  #200 $finish;
 end

 always begin
  #5 clk = ~clk;
 end

 //PRINT SEQUENCE
  always @ (posedge clk)
  $write("%b ",s3);    
endmodule

Sequence.vcd
$date
	Tue Nov 26 09:24:38 2019
$end
$version
	Icarus Verilog
$end
$timescale
	1ps
$end
$scope module Test_sequencegenerator $end
$var wire 1 ! s3 $end
$var reg 1 " clk $end
$var reg 1 # reset $end
$scope module SGT $end
$var wire 1 $ clk $end
$var wire 1 % reset $end
$var wire 1 & s0 $end
$var reg 1 ' s1 $end
$var reg 1 ( s2 $end
$var reg 1 ) s3 $end
$upscope $end
$upscope $end
$enddefinitions $end
#0
$dumpvars
x)
x(
x'
x&
0%
0$
0#
0"
x!
$end
#5000
1"
1$
#10000
1&
0)
0!
0(
1'
0"
0$
1#
1%
#15000
1"
1$
#20000
1(
0"
0$
0#
0%
#25000
0&
1)
1!
1"
1$
#30000
0"
0$
#35000
1&
0'
1"
1$
#40000
0"
0$
#45000
0&
0(
1'
1"
1$
#50000
0"
0$
#55000
0)
0!
1(
0'
1"
1$
#60000
0"
0$
#65000
1&
1)
1!
0(
1"
1$
#70000
0"
0$
#75000
0)
0!
1'
1"
1$
#80000
0"
0$
#85000
1(
1"
1$
#90000
0"
0$
#95000
0&
1)
1!
1"
1$
#100000
0"
0$
#105000
1&
0'
1"
1$
#110000
0"
0$
#115000
0&
0(
1'
1"
1$
#120000
0"
0$
#125000
0)
0!
1(
0'
1"
1$
#130000
0"
0$
#135000
1&
1)
1!
0(
1"
1$
#140000
0"
0$
#145000
0)
0!
1'
1"
1$
#150000
0"
0$
#155000
1(
1"
1$
#160000
0"
0$
#165000
0&
1)
1!
1"
1$
#170000
0"
0$
#175000
1&
0'
1"
1$
#180000
0"
0$
#185000
0&
0(
1'
1"
1$
#190000
0"
0$
#195000
0)
0!
1(
0'
1"
1$
#200000
0"
0$
#205000
1&
1)
1!
0(
1"
1$
#210000
0"
0$
#215000
0)
0!
1'
1"
1$
